best_arm/__init__.py
best_arm/bandit.py
best_arm/cli.py
best_arm/environment.py
best_arm/experiments.py
best_arm/model.py
best_arm/stopping_conditions.py
best_arm/utils.py
best_arm/algorithms/__init__.py
best_arm/algorithms/adahedge.py
best_arm/algorithms/exp_gap_elim.py
best_arm/algorithms/frank_wolfe.py
best_arm/algorithms/gradient_ascent.py
best_arm/algorithms/lil_ucb.py
best_arm/algorithms/lucb1.py
best_arm/algorithms/top_two.py
best_arm/algorithms/track_and_stop.py
best_arm-0.1.1.dist-info/licenses/LICENSE
best_arm-0.1.1.dist-info/METADATA
best_arm-0.1.1.dist-info/WHEEL
best_arm-0.1.1.dist-info/entry_points.txt
best_arm-0.1.1.dist-info/top_level.txt
best_arm-0.1.1.dist-info/RECORD
